Metadata-Version: 2.1
Name: NodeGraphQt_QuiltiX_fork
Version: 0.7.0
Summary: [Fork] Node graph framework for PySide6 that can be
Home-page: https://github.com/manuelkoester/NodeGraphQt/tree/qtpy
Author: Johnny Chan, Manuel Koester, Richard Frangenberg
License: MIT License
Project-URL: Documentation, https://jchanvfx.github.io/NodeGraphQt/api/html/index.html
Project-URL: Source, https://github.com/jchanvfx/NodeGraphQt/
Project-URL: Tracker, https://github.com/jchanvfx/NodeGraphQt/issues
Classifier: Operating System :: OS Independent
Classifier: License :: OSI Approved :: MIT License
Classifier: Programming Language :: Python :: 3.9
Requires-Python: >=3.9
License-File: LICENSE.md
Requires-Dist: qtpy >=2.3.0
Provides-Extra: pyside6
Requires-Dist: PySide6 <6.7.0 ; extra == 'pyside6'
